powernovo2/__init__.py
powernovo2/denovo.py
powernovo2/inference.py
powernovo2/config/__init__.py
powernovo2/config/default_config.py
powernovo2/knapsack/__init__.py
powernovo2/knapsack/cbc_solver.py
powernovo2/knapsack/knapsack_solver.py
powernovo2/models/__init__.py
powernovo2/models/base_model.py
powernovo2/modules/__init__.py
powernovo2/modules/data/__init__.py
powernovo2/modules/data/parsers.py
powernovo2/modules/data/peptide_datasets.py
powernovo2/modules/data/preprocessing.py
powernovo2/modules/data/primitives.py
powernovo2/modules/data/spectrum_datasets.py
powernovo2/modules/data/utils.py
powernovo2/modules/flows/__init__.py
powernovo2/modules/flows/coupling.py
powernovo2/modules/flows/generative_flow.py
powernovo2/modules/flows/lengths_predictor.py
powernovo2/modules/flows/linear.py
powernovo2/modules/flows/posterior.py
powernovo2/modules/flows/prior.py
powernovo2/modules/flows/utils.py
powernovo2/modules/tokenizers/__init__.py
powernovo2/modules/tokenizers/peptides.py
powernovo2/modules/tokenizers/tokenizer.py
powernovo2/modules/transformers/__init__.py
powernovo2/modules/transformers/attention.py
powernovo2/modules/transformers/criterion.py
powernovo2/modules/transformers/layer_norm.py
powernovo2/modules/transformers/positional_encoding.py
powernovo2/modules/transformers/spectra.py
powernovo2/modules/transformers/transformer.py
powernovo2/peptides/__init__.py
powernovo2/peptides/peptide_aggregator.py
powernovo2/proteins/__init__.py
powernovo2/proteins/greedy_solver.py
powernovo2/proteins/output_builder.py
powernovo2/proteins/protein_inference.py
powernovo2/proteins/protein_merger.py
powernovo2/proteins/psm_network.py
powernovo2/proteins/sequences_tagger.py
powernovo2/utils/__init__.py
powernovo2/utils/utils.py
powernovo2-1.0.14.dist-info/LICENSE
powernovo2-1.0.14.dist-info/METADATA
powernovo2-1.0.14.dist-info/WHEEL
powernovo2-1.0.14.dist-info/top_level.txt
powernovo2-1.0.14.dist-info/RECORD
