Metadata-Version: 2.1
Name: powernovo2
Version: 1.0.14
Summary: PowerNovo2: A generative flow-based approach to non-autoregressive de novo peptide sequencing
Home-page: https://github.com/protdb/PowerNovo2.git
Author: Denis Petrovskiy
Author-email: petro2017@mail.ru
License: MIT
Requires-Python: >=3.8
License-File: LICENSE
Requires-Dist: appdirs ==1.4.4
Requires-Dist: attrs ==25.1.0
Requires-Dist: biopython ==1.85
Requires-Dist: contourpy ==1.3.0
Requires-Dist: cycler ==0.12.1
Requires-Dist: cylp ==0.92.3
Requires-Dist: dill ==0.3.9
Requires-Dist: einops ==0.8.1
Requires-Dist: exceptiongroup ==1.2.2
Requires-Dist: fastobo ==0.13.0
Requires-Dist: filelock ==3.17.0
Requires-Dist: fonttools ==4.56.0
Requires-Dist: fsspec ==2025.2.0
Requires-Dist: h5py ==3.13.0
Requires-Dist: hypothesis ==6.127.2
Requires-Dist: importlib-resources ==6.5.2
Requires-Dist: Jinja2 ==3.1.5
Requires-Dist: kiwisolver ==1.4.7
Requires-Dist: lark ==1.2.2
Requires-Dist: llvmlite ==0.43.0
Requires-Dist: lxml ==5.3.1
Requires-Dist: MarkupSafe ==3.0.2
Requires-Dist: mpmath ==1.3.0
Requires-Dist: networkx ==3.2.1
Requires-Dist: npysearch ==1.3.1
Requires-Dist: numba ==0.60.0
Requires-Dist: numpy ==1.26.4
Requires-Dist: packaging ==24.2
Requires-Dist: pandas >=2.2.2
Requires-Dist: pillow ==11.1.0
Requires-Dist: pyparsing ==3.2.1
Requires-Dist: pyteomics ==4.7.5
Requires-Dist: python-dateutil ==2.9.0.post0
Requires-Dist: pytz ==2025.1
Requires-Dist: scipy ==1.13.1
Requires-Dist: selfies ==2.2.0
Requires-Dist: six ==1.17.0
Requires-Dist: sortedcontainers ==2.4.0
Requires-Dist: spectrum-utils ==0.4.2
Requires-Dist: sympy ==1.13.1
Requires-Dist: torch >=2.5.0
Requires-Dist: tqdm ==4.67.1
Requires-Dist: triton ==3.2.0
Requires-Dist: typing-extensions ==4.12.2
Requires-Dist: tzdata ==2025.1
Requires-Dist: zipp ==3.21.0
Requires-Dist: pytorch-lightning ~=2.5.0.post0
Requires-Dist: torchmetrics ~=1.6.1
Requires-Dist: requests ~=2.32.3
